{"frame_0":{"version":"2.3.0","objects":[{"type":"group","version":"2.3.0","originX":"left","originY":"top","left":0,"top":0,"width":500,"height":264.3,"fill":"#272c33","stroke":null,"strokeWidth":0,"strokeDashArray":null,"strokeLineCap":"butt","strokeLineJoin":"miter","strokeMiterLimit":10,"scaleX":0.4,"scaleY":0.45,"angle":0,"flipX":false,"flipY":false,"opacity":1,"shadow":null,"visible":true,"clipTo":null,"backgroundColor":"","fillRule":"nonzero","paintFirst":"fill","globalCompositeOperation":"source-over","transformMatrix":null,"skewX":0,"skewY":0,"itemId":1528877057578,"selectable":false,"lockMovementX":false,"lockMovementY":false,"lockScalingX":false,"lockScalingY":false,"lockRotation":false,"objects":[]},{"type":"i-text","version":"2.3.0","originX":"left","originY":"top","left":9.17,"top":3.12,"width":96.9,"height":22.6,"fill":"#404762","stroke":null,"strokeWidth":1,"strokeDashArray":null,"strokeLineCap":"butt","strokeLineJoin":"miter","strokeMiterLimit":10,"scaleX":1.77,"scaleY":1.77,"angle":0,"flipX":false,"flipY":false,"opacity":1,"shadow":null,"visible":true,"clipTo":null,"backgroundColor":"","fillRule":"nonzero","paintFirst":"fill","globalCompositeOperation":"source-over","transformMatrix":null,"skewX":0,"skewY":0,"text":"PRACTICE","fontSize":20,"fontWeight":"bold","fontFamily":"Josefin Sans","fontStyle":"normal","lineHeight":1.16,"underline":false,"overline":false,"linethrough":false,"textAlign":"left","textBackgroundColor":"","charSpacing":0,"itemId":1528877059258,"selectable":true,"lockMovementX":false,"lockMovementY":false,"lockScalingX":false,"lockScalingY":false,"lockRotation":true,"styles":{}},{"type":"i-text","version":"2.3.0","originX":"left","originY":"top","left":9.17,"top":47.41,"width":70.86,"height":22.6,"fill":"#404762","stroke":null,"strokeWidth":1,"strokeDashArray":null,"strokeLineCap":"butt","strokeLineJoin":"miter","strokeMiterLimit":10,"scaleX":1.77,"scaleY":1.77,"angle":0,"flipX":false,"flipY":false,"opacity":1,"shadow":null,"visible":true,"clipTo":null,"backgroundColor":"","fillRule":"nonzero","paintFirst":"fill","globalCompositeOperation":"source-over","transformMatrix":null,"skewX":0,"skewY":0,"text":"MAKES","fontSize":20,"fontWeight":"bold","fontFamily":"Josefin Sans","fontStyle":"normal","lineHeight":1.16,"underline":false,"overline":false,"linethrough":false,"textAlign":"left","textBackgroundColor":"","charSpacing":0,"itemId":1528877059562,"selectable":true,"lockMovementX":false,"lockMovementY":false,"lockScalingX":false,"lockScalingY":false,"lockRotation":true,"styles":{}},{"type":"i-text","version":"2.3.0","originX":"left","originY":"top","left":9.17,"top":86.96,"width":88.52,"height":22.6,"fill":"#404762","stroke":null,"strokeWidth":1,"strokeDashArray":null,"strokeLineCap":"butt","strokeLineJoin":"miter","strokeMiterLimit":10,"scaleX":1.46,"scaleY":1.46,"angle":0,"flipX":false,"flipY":false,"opacity":1,"shadow":null,"visible":true,"clipTo":null,"backgroundColor":"","fillRule":"nonzero","paintFirst":"fill","globalCompositeOperation":"source-over","transformMatrix":null,"skewX":0,"skewY":0,"text":"PERFECT","fontSize":20,"fontWeight":"normal","fontFamily":"Josefin Sans","fontStyle":"normal","lineHeight":1.16,"underline":false,"overline":false,"linethrough":false,"textAlign":"left","textBackgroundColor":"","charSpacing":0,"itemId":1528877058949,"selectable":true,"lockMovementX":false,"lockMovementY":false,"lockScalingX":false,"lockScalingY":false,"lockRotation":true,"styles":{}}]}}